adder.v
module adder (
    input  wire [31:0] a,
    input  wire [31:0] b,
    output wire [31:0] y
);
    assign y = a + b;
endmodule

dmem.v
module dmem (
    input  wire        clk,
    input  wire        we,
    input  wire [31:0] addr,
    input  wire [31:0] wd,
    output wire [31:0] rd
);
    reg [31:0] mem [0:65535];

    always @(posedge clk) begin
        if (we)
            mem[addr[17:2]] <= wd;
    end

    assign rd = mem[addr[17:2]];

endmodule

alu.v
module alu (
    input  wire [31:0] a,
    input  wire [31:0] b,
    input  wire [3:0]  alu_control, // width depends on your design
    output reg  [31:0] y,
    output wire        zero
);
    assign zero = (y == 32'b0);

    always @(*) begin
        case (alu_control)
            4'b0000: y = a + b;                   // add
            4'b0001: y = a - b;                   // sub
            4'b0010: y = a << b[4:0];             // sll
            4'b0011: y = ($signed(a) < $signed(b)) ? 32'b1 : 32'b0; // slt
            4'b0100: y = (a < b) ? 32'b1 : 32'b0; // sltu
            4'b0101: y = a ^ b;                   // xor
            4'b0110: y = a >> b[4:0];             // srl (logical)
            4'b0111: y = $signed(a) >>> b[4:0];   // sra (arithmetic)
            4'b1000: y = a | b;                   // or
            4'b1001: y = a & b;                   // and
            default: y = 32'b0;
        endcase
    end

endmodule

mux2.v
module mux2 #(parameter WIDTH = 32) (
    input  wire [WIDTH-1:0] a,
    input  wire [WIDTH-1:0] b,
    input  wire             sel,
    output wire [WIDTH-1:0] y
);
    assign y = sel ? b : a;
endmodule

sign_ext.v
module sign_ext (
    input  wire [31:0] instr,
    input  wire [2:0]  imm_sel,
    output reg  [31:0] imm
);

    always @(*) begin
        case (imm_sel)

            // I-type
            3'b000: imm = {{20{instr[31]}}, instr[31:20]};

            // S-type
            3'b001: imm = {{20{instr[31]}}, instr[31:25], instr[11:7]};

            // B-type (branch)
            3'b010: imm = {{19{instr[31]}},
                           instr[31],
                           instr[7],
                           instr[30:25],
                           instr[11:8],
                           1'b0};

            // U-type (lui)
            3'b011: imm = {instr[31:12], 12'b0};

            // J-type (jal)
            3'b100: imm = {{11{instr[31]}},
                           instr[31],
                           instr[19:12],
                           instr[20],
                           instr[30:21],
                           1'b0};

            default: imm = 32'b0;

        endcase
    end

endmodule

regfile.v
module regfile (
    input  wire        clk,
    input  wire        we,
    input  wire [4:0]  rs1, rs2, rd,
    input  wire [31:0] wd,
    output wire [31:0] rd1, rd2
);
    reg [31:0] regs [31:0];

    // write
    always @(posedge clk) begin
        if (we && rd != 0)
            regs[rd] <= wd;
    end

    // read
    assign rd1 = (rs1 == 0) ? 0 : regs[rs1];
    assign rd2 = (rs2 == 0) ? 0 : regs[rs2];

endmodule

controller.v
module controller (
    input  wire [6:0] opcode,
    input  wire [2:0] funct3,
    input  wire [6:0] funct7,

    output reg        rf_we,
    output reg [2:0]  imm_sel,
    output reg        sel_alu_src_b,
    output reg        dmem_we,
    output reg [1:0]  sel_result,
    output reg [1:0]  alu_op,
    output reg [3:0]  alu_control,
    output reg        branch,
    output reg        jump
);

    always @(*) begin
        rf_we         = 0;
        imm_sel       = 3'b000;
        sel_alu_src_b = 0;
        dmem_we       = 0;
        sel_result    = 2'b00;
        alu_op        = 2'b00;
        branch        = 0;
        jump          = 0;

        case (opcode)
            7'b0110011: begin
                rf_we         = 1;
                sel_alu_src_b = 0;
                sel_result    = 2'b00;
                alu_op        = 2'b01;
            end
            7'b0010011: begin
                rf_we         = 1;
                imm_sel       = 3'b000;
                sel_alu_src_b = 1;
                sel_result    = 2'b00;
                alu_op        = 2'b10;
            end
            7'b0000011: begin
                rf_we         = 1;
                imm_sel       = 3'b000;
                sel_alu_src_b = 1;
                sel_result    = 2'b01;
                alu_op        = 2'b00;
            end
            7'b0100011: begin
                imm_sel       = 3'b001;
                sel_alu_src_b = 1;
                dmem_we       = 1;
                alu_op        = 2'b00;
            end
            7'b1100011: begin
                branch        = 1;
                imm_sel       = 3'b010;
                sel_alu_src_b = 0;
                alu_op        = 2'b11;
            end
            7'b1101111: begin
                jump          = 1;
                rf_we         = 1;
                imm_sel       = 3'b100;
                sel_result    = 2'b10;
            end
            7'b0110111: begin
                rf_we         = 1;
                imm_sel       = 3'b011;
                sel_result    = 2'b11;
            end
        endcase
    end

    always @(*) begin
        alu_control = 4'b0000;

        case (alu_op)

            2'b00: alu_control = 4'b0000;

            2'b01: begin
                case (funct3)
                    3'b000: alu_control = (funct7 == 7'b0100000) ? 4'b0001 : 4'b0000;
                    3'b001: alu_control = 4'b0010;
                    3'b010: alu_control = 4'b0011;
                    3'b011: alu_control = 4'b0100;
                    3'b100: alu_control = 4'b0101;
                    3'b101: alu_control = (funct7 == 7'b0100000) ? 4'b0111 : 4'b0110;
                    3'b110: alu_control = 4'b1000;
                    3'b111: alu_control = 4'b1001;
                endcase
            end

            2'b10: begin
                case (funct3)
                    3'b000: alu_control = 4'b0000;
                    3'b010: alu_control = 4'b0011;
                    3'b011: alu_control = 4'b0100;
                    3'b100: alu_control = 4'b0101;
                    3'b110: alu_control = 4'b1000;
                    3'b111: alu_control = 4'b1001;
                    3'b001: alu_control = 4'b0010;
                    3'b101: alu_control = (funct7 == 7'b0100000) ? 4'b0111 : 4'b0110;
                endcase
            end

            2'b11: begin
                case (funct3)
                    3'b000: alu_control = 4'b0001;
                    default: alu_control = 4'b0000;
                endcase
            end

        endcase
    end

endmodule

imem.v
module imem (
    input  wire [31:0] addr,
    output wire [31:0] instr
);
    reg [31:0] mem [0:255];

    initial begin
        $readmemh("program.hex", mem);
    end

    assign instr = mem[addr[31:2]];

endmodule

pc.v
// pc.v
module pc (
    input  wire        clk,
    input  wire        reset,
    input  wire [31:0] next_pc,
    output reg  [31:0] pc
);

    always @(posedge clk) begin
        if (reset)
            pc <= 32'b0;
        else
            pc <= next_pc;
    end

endmodule

cpu_top.v
`include "alu.v"
`include "controller.v"
`include "pc.v"
`include "imem.v"
`include "regfile.v"
`include "dmem.v"
`include "sign_ext.v"
`include "adder.v"
`include "mux2.v"   

module cpu_top (
    input wire clk,
    input wire reset
);

    wire [31:0] pc, next_pc, pc_plus_4, pc_branch, pc_jump;

    wire [31:0] instr;


    wire [6:0] opcode = instr[6:0];
    wire [4:0] rd     = instr[11:7];
    wire [2:0] funct3 = instr[14:12];
    wire [4:0] rs1    = instr[19:15];
    wire [4:0] rs2    = instr[24:20];
    wire [6:0] funct7 = instr[31:25];

    wire        rf_we, sel_alu_src_b, dmem_we;
    wire [2:0]  imm_sel;
    wire [1:0]  sel_result;
    wire [1:0]  alu_op;
    wire [3:0]  alu_control;
    wire        branch, jump;

    wire [31:0] rd1, rd2;
    wire [31:0] imm;
    wire [31:0] alu_b_src;
    wire [31:0] alu_y;
    wire        alu_zero;
    wire [31:0] dmem_rd;
    wire [31:0] result;
    wire        take_branch;
    wire [31:0] pc_target;


    pc u_pc (
        .clk(clk),
        .reset(reset),
        .next_pc(next_pc),
        .pc(pc)
    );


    adder u_pc_adder (
        .a(pc),
        .b(32'd4),
        .y(pc_plus_4)
    );


    imem u_imem (
        .addr(pc),
        .instr(instr)
    );


    controller u_controller (
        .opcode(opcode),
        .funct3(funct3),
        .funct7(funct7),
        .rf_we(rf_we),
        .imm_sel(imm_sel),
        .sel_alu_src_b(sel_alu_src_b),
        .dmem_we(dmem_we),
        .sel_result(sel_result),
        .alu_control(alu_control),
        .branch(branch),
        .jump(jump)
    );


    regfile u_regfile (
        .clk(clk),
        .we(rf_we),
        .rs1(rs1),
        .rs2(rs2),
        .rd(rd),
        .wd(result),
        .rd1(rd1),
        .rd2(rd2)
    );

    sign_ext u_sign_ext (
        .instr(instr),
        .imm_sel(imm_sel),
        .imm(imm)
    );


    mux2 #(32) u_alu_src_mux (
        .a(rd2),
        .b(imm),
        .sel(sel_alu_src_b),
        .y(alu_b_src)
    );


    alu u_alu (
        .a(rd1),
        .b(alu_b_src),
        .alu_control(alu_control),
        .y(alu_y),
        .zero(alu_zero)
    );


    dmem u_dmem (
        .clk(clk),
        .we(dmem_we),
        .addr(alu_y),
        .wd(rd2),       
        .rd(dmem_rd)
    );


    wire [31:0] sel_res0 = (sel_result == 2'b00) ? alu_y   :
                           (sel_result == 2'b01) ? dmem_rd : 32'b0;

    wire [31:0] sel_res1 = (sel_result == 2'b10) ? pc_plus_4 :
                           (sel_result == 2'b11) ? imm       : 32'b0;

    assign result = (sel_result[1] == 1'b0) ? sel_res0 : sel_res1;


    adder u_branch_adder (
        .a(pc),
        .b(imm),
        .y(pc_target)
    );

    assign take_branch = branch && alu_zero;


    assign next_pc = jump        ? pc_target :
                     take_branch ? pc_target :
                                   pc_plus_4;

endmodule

tb_cpu.v
`timescale 1ns/1ps
`include "cpu_top.v"

module tb_cpu;
    reg clk;
    reg reset;

    cpu_top dut (
        .clk(clk),
        .reset(reset)
    );

    // clock generation: 10ns period
    initial begin
        clk = 0;
        forever #5 clk = ~clk;
    end

    // reset sequence
    initial begin
        reset = 1;
        #20;
        reset = 0;
    end

    // simulation control
    initial begin
        $dumpfile("cpu_wave.vcd");
        $dumpvars(0, tb_cpu);

        // run long enough to execute your program
        #2000;
        $finish;
    end

endmodule

cpu_wave.vcd
$date
	Fri Dec  5 23:10:18 2025
$end
$version
	Icarus Verilog
$end
$timescale
	1ps
$end
$scope module tb_cpu $end
$var reg 1 ! clk $end
$var reg 1 " reset $end
$scope module dut $end
$var wire 1 ! clk $end
$var wire 1 " reset $end
$var wire 1 # take_branch $end
$var wire 2 $ sel_result [1:0] $end
$var wire 32 % sel_res1 [31:0] $end
$var wire 32 & sel_res0 [31:0] $end
$var wire 1 ' sel_alu_src_b $end
$var wire 5 ( rs2 [4:0] $end
$var wire 5 ) rs1 [4:0] $end
$var wire 1 * rf_we $end
$var wire 32 + result [31:0] $end
$var wire 32 , rd2 [31:0] $end
$var wire 32 - rd1 [31:0] $end
$var wire 5 . rd [4:0] $end
$var wire 32 / pc_target [31:0] $end
$var wire 32 0 pc_plus_4 [31:0] $end
$var wire 32 1 pc [31:0] $end
$var wire 7 2 opcode [6:0] $end
$var wire 32 3 next_pc [31:0] $end
$var wire 1 4 jump $end
$var wire 32 5 instr [31:0] $end
$var wire 3 6 imm_sel [2:0] $end
$var wire 32 7 imm [31:0] $end
$var wire 7 8 funct7 [6:0] $end
$var wire 3 9 funct3 [2:0] $end
$var wire 1 : dmem_we $end
$var wire 32 ; dmem_rd [31:0] $end
$var wire 1 < branch $end
$var wire 1 = alu_zero $end
$var wire 32 > alu_y [31:0] $end
$var wire 4 ? alu_control [3:0] $end
$var wire 32 @ alu_b_src [31:0] $end
$scope module u_alu $end
$var wire 1 = zero $end
$var wire 32 A b [31:0] $end
$var wire 4 B alu_control [3:0] $end
$var wire 32 C a [31:0] $end
$var reg 32 D y [31:0] $end
$upscope $end
$scope module u_alu_src_mux $end
$var wire 32 E y [31:0] $end
$var wire 1 ' sel $end
$var wire 32 F b [31:0] $end
$var wire 32 G a [31:0] $end
$var parameter 32 H WIDTH $end
$upscope $end
$scope module u_branch_adder $end
$var wire 32 I y [31:0] $end
$var wire 32 J b [31:0] $end
$var wire 32 K a [31:0] $end
$upscope $end
$scope module u_controller $end
$var wire 3 L funct3 [2:0] $end
$var wire 7 M funct7 [6:0] $end
$var wire 7 N opcode [6:0] $end
$var reg 4 O alu_control [3:0] $end
$var reg 2 P alu_op [1:0] $end
$var reg 1 < branch $end
$var reg 1 : dmem_we $end
$var reg 3 Q imm_sel [2:0] $end
$var reg 1 4 jump $end
$var reg 1 * rf_we $end
$var reg 1 ' sel_alu_src_b $end
$var reg 2 R sel_result [1:0] $end
$upscope $end
$scope module u_dmem $end
$var wire 32 S addr [31:0] $end
$var wire 1 ! clk $end
$var wire 32 T rd [31:0] $end
$var wire 1 : we $end
$var wire 32 U wd [31:0] $end
$upscope $end
$scope module u_imem $end
$var wire 32 V instr [31:0] $end
$var wire 32 W addr [31:0] $end
$upscope $end
$scope module u_pc $end
$var wire 1 ! clk $end
$var wire 32 X next_pc [31:0] $end
$var wire 1 " reset $end
$var reg 32 Y pc [31:0] $end
$upscope $end
$scope module u_pc_adder $end
$var wire 32 Z a [31:0] $end
$var wire 32 [ b [31:0] $end
$var wire 32 \ y [31:0] $end
$upscope $end
$scope module u_regfile $end
$var wire 1 ! clk $end
$var wire 5 ] rd [4:0] $end
$var wire 5 ^ rs1 [4:0] $end
$var wire 5 _ rs2 [4:0] $end
$var wire 32 ` wd [31:0] $end
$var wire 1 * we $end
$var wire 32 a rd2 [31:0] $end
$var wire 32 b rd1 [31:0] $end
$upscope $end
$scope module u_sign_ext $end
$var wire 3 c imm_sel [2:0] $end
$var wire 32 d instr [31:0] $end
$var reg 32 e imm [31:0] $end
$upscope $end
$upscope $end
$upscope $end
$enddefinitions $end
$comment Show the parameter values. $end
$dumpall
b100000 H
$end
#0
$dumpvars
bx e
bx d
bx c
bx b
bx a
bx `
bx _
bx ^
bx ]
bx \
b100 [
bx Z
bx Y
bx X
bx W
bx V
bx U
bx T
bx S
bx R
bx Q
bx P
bx O
bx N
bx M
bx L
bx K
bx J
bx I
bx G
bx F
bx E
bx D
bx C
bx B
bx A
bx @
bx ?
bx >
x=
x<
bx ;
x:
bx 9
bx 8
bx 7
bx 6
bx 5
x4
bx 3
bx 2
bx 1
bx 0
bx /
bx .
bx -
bx ,
bx +
x*
bx )
bx (
x'
bx &
bx %
bx $
x#
1"
0!
$end
#5000
b10000000000000000 +
b10000000000000000 `
b0 &
0#
b10000000000000000 %
b100 3
b100 X
b0 @
b0 A
b0 E
b0 ,
b0 G
b0 U
b0 a
b0 ?
b0 B
b0 O
04
0<
b0 P
b11 $
b11 R
0:
0'
b11 6
b11 Q
b11 c
1*
b10000000000000000 /
b10000000000000000 I
b10000000000000000 7
b10000000000000000 F
b10000000000000000 J
b10000000000000000 e
b0 8
b0 M
b0 (
b0 _
b10 )
b10 ^
b0 9
b0 L
b1 .
b1 ]
b110111 2
b110111 N
b10000000010110111 5
b10000000010110111 V
b10000000010110111 d
b100 0
b100 \
b0 1
b0 K
b0 W
b0 Y
b0 Z
1!
#10000
0!
#15000
1!
#20000
0!
0"
#25000
b10000000000000101 +
b10000000000000101 `
b0 %
0=
b10000000000000101 >
b10000000000000101 D
b10000000000000101 S
b101 @
b101 A
b101 E
b10000000000000101 &
bx ,
bx G
bx U
bx a
b10000000000000000 -
b10000000000000000 C
b10000000000000000 b
b10 P
1'
b0 $
b0 R
b0 6
b0 Q
b0 c
1*
b1000 3
b1000 X
b101 7
b101 F
b101 J
b101 e
b101 (
b101 _
b1 )
b1 ^
b10011 2
b10011 N
b10100001000000010010011 5
b10100001000000010010011 V
b10100001000000010010011 d
b1000 0
b1000 \
b1001 /
b1001 I
b100 1
b100 K
b100 W
b100 Y
b100 Z
1!
#30000
0!
#35000
b10100 +
b10100 `
b10100 &
b10100 @
b10100 A
b10100 E
b10100 >
b10100 D
b10100 S
b1100 3
b1100 X
b10100 7
b10100 F
b10100 J
b10100 e
b10100 (
b10100 _
b0 )
b0 ^
b10 .
b10 ]
b0 -
b0 C
b0 b
b1010000000000000100010011 5
b1010000000000000100010011 V
b1010000000000000100010011 d
b1100 0
b1100 \
b11100 /
b11100 I
b1000 1
b1000 K
b1000 W
b1000 Y
b1000 Z
1!
#40000
0!
#45000
b10000000000000101 +
b10000000000000101 `
b10000000000000101 &
b10000000000000101 >
b10000000000000101 D
b10000000000000101 S
b0 @
b0 A
b0 E
b10100 ,
b10100 G
b10100 U
b10100 a
b10000000000000101 -
b10000000000000101 C
b10000000000000101 b
1:
b1 6
b1 Q
b1 c
b0 P
1'
0*
b10000 3
b10000 X
b0 7
b0 F
b0 J
b0 e
b10 (
b10 _
b1 )
b1 ^
b10 9
b10 L
b0 .
b0 ]
b100011 2
b100011 N
b1000001010000000100011 5
b1000001010000000100011 V
b1000001010000000100011 d
b10000 0
b10000 \
b1100 /
b1100 I
b1100 1
b1100 K
b1100 W
b1100 Y
b1100 Z
1!
#50000
0!
#55000
b10100 +
b10100 `
b10000000000000101 >
b10000000000000101 D
b10000000000000101 S
b10100 &
b0 @
b0 A
b0 E
b0 ,
b0 G
b0 U
b0 a
b1 $
b1 R
1*
0:
1'
b0 6
b0 Q
b0 c
b10100 3
b10100 X
b0 7
b0 F
b0 J
b0 e
b0 (
b0 _
b11 .
b11 ]
b11 2
b11 N
b1010000110000011 5
b1010000110000011 V
b1010000110000011 d
b10100 ;
b10100 T
b10100 0
b10100 \
b10000 /
b10000 I
b10000 1
b10000 K
b10000 W
b10000 Y
b10000 Z
1!
#60000
0!
#65000
bx ;
bx T
b101000 +
b101000 `
b101000 >
b101000 D
b101000 S
b101000 &
b10100 @
b10100 A
b10100 E
b10100 ,
b10100 G
b10100 U
b10100 a
b10100 -
b10100 C
b10100 b
b1 P
b0 $
b0 R
0'
1*
b11000 3
b11000 X
b10 7
b10 F
b10 J
b10 e
b10 (
b10 _
b11 )
b11 ^
b0 9
b0 L
b100 .
b100 ]
b110011 2
b110011 N
b1000011000001000110011 5
b1000011000001000110011 V
b1000011000001000110011 d
b11000 0
b11000 \
b10110 /
b10110 I
b10100 1
b10100 K
b10100 W
b10100 Y
b10100 Z
1!
#70000
0!
#75000
b10100 +
b10100 `
b10100 &
b10100 >
b10100 D
b10100 S
b1 ?
b1 B
b1 O
b101000 -
b101000 C
b101000 b
b11100 3
b11100 X
b10000000011 7
b10000000011 F
b10000000011 J
b10000000011 e
b100000 8
b100000 M
b11 (
b11 _
b100 )
b100 ^
b101 .
b101 ]
b1000000001100100000001010110011 5
b1000000001100100000001010110011 V
b1000000001100100000001010110011 d
b11100 0
b11100 \
b10000011011 /
b10000011011 I
b11000 1
b11000 K
b11000 W
b11000 Y
b11000 Z
1!
#80000
0!
#85000
b0 +
b0 `
1#
b0 &
1=
b0 >
b0 D
b0 S
b1 ?
b1 B
b1 O
b10100 -
b10100 C
b10100 b
b10 6
b10 Q
b10 c
1<
b11 P
0*
b101000 3
b101000 X
b1100 7
b1100 F
b1100 J
b1100 e
b0 8
b0 M
b101 )
b101 ^
b1100 .
b1100 ]
b1100011 2
b1100011 N
b1100101000011001100011 5
b1100101000011001100011 V
b1100101000011001100011 d
b100000 0
b100000 \
b101000 /
b101000 I
b11100 1
b11100 K
b11100 W
b11100 Y
b11100 Z
1!
#90000
0!
#95000
b101010 +
b101010 `
b101010 &
0=
b101010 >
b101010 D
b101010 S
b101010 @
b101010 A
b101010 E
0#
b0 ?
b0 B
b0 O
bx ,
bx G
bx U
bx a
b0 -
b0 C
b0 b
1'
1*
0<
b10 P
b0 6
b0 Q
b0 c
b101010 7
b101010 F
b101010 J
b101010 e
b1 8
b1 M
b1010 (
b1010 _
b0 )
b0 ^
b110 .
b110 ]
b10011 2
b10011 N
b101100 3
b101100 X
b10101000000000001100010011 5
b10101000000000001100010011 V
b10101000000000001100010011 d
b101100 0
b101100 \
b1010010 /
b1010010 I
b101000 1
b101000 K
b101000 W
b101000 Y
b101000 Z
1!
#100000
0!
#105000
b110000 +
b110000 `
1=
b0 >
b0 D
b0 S
b110000 %
b0 &
b0 @
b0 A
b0 E
b0 ,
b0 G
b0 U
b0 a
b10 $
b10 R
b100 6
b100 Q
b100 c
14
b0 P
0'
1*
b101100 3
b101100 X
b0 7
b0 F
b0 J
b0 e
b0 8
b0 M
b0 (
b0 _
b0 .
b0 ]
b1101111 2
b1101111 N
b1101111 5
b1101111 V
b1101111 d
b110000 0
b110000 \
b101100 /
b101100 I
b101100 1
b101100 K
b101100 W
b101100 Y
b101100 Z
1!
