controller.v
module controller (
    input        clk,
    input        rst,
    input  [6:0] opcode,

    output reg        sel_mem_addr,   // 0 = PC, 1 = ALU
    output reg        ir_we,
    output reg        pc_update,
    output reg        mem_we,
    output reg        rf_we,
    output reg        sel_alu_src_a,   // 0 = PC, 1 = rs1
    output reg [1:0]  sel_alu_src_b,   // 00 = rs2, 01 = imm, 10 = 4
    output reg [1:0]  alu_op,          // to ALU decoder
    output reg [1:0]  sel_result       // 00 = ALU, 01 = MEM, 10 = PC+4, 11 = IMM(U)
);

    // -------------------------------------------------
    // STATE ENCODING (binary, pure Verilog)
    // -------------------------------------------------
    localparam S0_FETCH   = 4'd0;
    localparam S1_DECODE  = 4'd1;
    localparam S2_EXE_ADR = 4'd2;
    localparam S3_MEM_RD  = 4'd3;
    localparam S4_WB_MEM  = 4'd4;
    localparam S5_MEM_WR  = 4'd5;
    localparam S6_EXE_R   = 4'd6;
    localparam S7_WB_ALU  = 4'd7;
    localparam S8_BEQ     = 4'd8;
    localparam S9_EXE_I   = 4'd9;
    localparam S10_JAL    = 4'd10;
    localparam S11_LUI    = 4'd11;

    reg [3:0] state;
    reg [3:0] next_state;

    // -------------------------------------------------
    // STATE REGISTER
    // -------------------------------------------------
    always @(posedge clk or posedge rst) begin
        if (rst)
            state <= S0_FETCH;
        else
            state <= next_state;
    end

    // -------------------------------------------------
    // NEXT STATE LOGIC
    // -------------------------------------------------
    always @(*) begin
        next_state = state;

        case (state)

            S0_FETCH:
                next_state = S1_DECODE;

            S1_DECODE: begin
                case (opcode)
                    7'b0000011: next_state = S2_EXE_ADR; // LW
                    7'b0100011: next_state = S2_EXE_ADR; // SW
                    7'b0110011: next_state = S6_EXE_R;   // R-type
                    7'b0010011: next_state = S9_EXE_I;   // I-type ALU
                    7'b1100011: next_state = S8_BEQ;     // BEQ
                    7'b1101111: next_state = S10_JAL;    // JAL
                    7'b0110111: next_state = S11_LUI;    // LUI
                    default:    next_state = S0_FETCH;
                endcase
            end

            S2_EXE_ADR:
                next_state = (opcode == 7'b0000011) ? S3_MEM_RD : S5_MEM_WR;

            S3_MEM_RD:
                next_state = S4_WB_MEM;

            S4_WB_MEM:
                next_state = S0_FETCH;

            S5_MEM_WR:
                next_state = S0_FETCH;

            S6_EXE_R:
                next_state = S7_WB_ALU;

            S9_EXE_I:
                next_state = S7_WB_ALU;

            S7_WB_ALU:
                next_state = S0_FETCH;

            S8_BEQ:
                next_state = S0_FETCH;

            S10_JAL:
                next_state = S0_FETCH;

            S11_LUI:
                next_state = S0_FETCH;

            default:
                next_state = S0_FETCH;

        endcase
    end

    // -------------------------------------------------
    // OUTPUT LOGIC (MOORE FSM)
    // -------------------------------------------------
    always @(*) begin
        // defaults
        sel_mem_addr  = 1'b0;
        ir_we         = 1'b0;
        pc_update     = 1'b0;
        mem_we        = 1'b0;
        rf_we         = 1'b0;
        sel_alu_src_a = 1'b0;
        sel_alu_src_b = 2'b00;
        alu_op        = 2'b00;
        sel_result    = 2'b00;

        case (state)

            // ---------------- FETCH ----------------
            S0_FETCH: begin
                sel_mem_addr  = 1'b0;   // memory address = PC
                ir_we         = 1'b1;   // load instruction
                sel_alu_src_a = 1'b0;   // A = PC
                sel_alu_src_b = 2'b10;  // B = 4
                alu_op        = 2'b00;  // ADD
                pc_update     = 1'b1;   // PC = PC + 4
            end

            // ----------- ADDRESS CALC --------------
            S2_EXE_ADR: begin
                sel_alu_src_a = 1'b1;   // rs1
                sel_alu_src_b = 2'b01;  // immediate
                alu_op        = 2'b00;  // ADD
            end

            // ------------ MEMORY READ --------------
            S3_MEM_RD: begin
                sel_mem_addr = 1'b1;    // address = ALU
            end

            // ------------ MEMORY WRITE -------------
            S5_MEM_WR: begin
                sel_mem_addr = 1'b1;
                mem_we       = 1'b1;
            end

            // ----------- WRITEBACK MEM --------------
            S4_WB_MEM: begin
                rf_we      = 1'b1;
                sel_result = 2'b01;     // data from memory
            end

            // ------------ R-TYPE EXEC --------------
            S6_EXE_R: begin
                sel_alu_src_a = 1'b1;
                sel_alu_src_b = 2'b00;
                alu_op        = 2'b10;
            end

            // ------------ I-TYPE EXEC --------------
            S9_EXE_I: begin
                sel_alu_src_a = 1'b1;
                sel_alu_src_b = 2'b01;
                alu_op        = 2'b10;
            end

            // ----------- WRITEBACK ALU --------------
            S7_WB_ALU: begin
                rf_we      = 1'b1;
                sel_result = 2'b00;
            end

            // ---------------- BEQ ------------------
            S8_BEQ: begin
                sel_alu_src_a = 1'b1;
                sel_alu_src_b = 2'b00;
                alu_op        = 2'b01;  // SUB
                pc_update     = 1'b1;   // datapath should gate with zero
            end

            // ---------------- JAL ------------------
            S10_JAL: begin
                sel_alu_src_a = 1'b0;   // PC
                sel_alu_src_b = 2'b01;  // immediate
                pc_update     = 1'b1;
                rf_we         = 1'b1;
                sel_result    = 2'b10;  // PC+4
            end

            // ---------------- LUI ------------------
            S11_LUI: begin
                rf_we      = 1'b1;
                sel_result = 2'b11;     // imm_u
            end

        endcase
    end

endmodule

alu_decoder.v
module alu_decoder (
    input  [1:0] alu_op,
    input  [2:0] funct3,
    input        funct7b5,
    output reg [3:0] alu_ctrl
);

    always @(*) begin
        case (alu_op)
            2'b00: alu_ctrl = 4'b0000; // ADD
            2'b01: alu_ctrl = 4'b0001; // SUB
            2'b10: begin
                case (funct3)
                    3'b000: alu_ctrl = funct7b5 ? 4'b0001 : 4'b0000;
                    3'b111: alu_ctrl = 4'b0010;
                    3'b110: alu_ctrl = 4'b0011;
                    3'b100: alu_ctrl = 4'b0100;
                    3'b010: alu_ctrl = 4'b0101;
                    3'b001: alu_ctrl = 4'b0110;
                    3'b101: alu_ctrl = funct7b5 ? 4'b1000 : 4'b0111;
                    default: alu_ctrl = 4'b0000;
                endcase
            end
            default: alu_ctrl = 4'b0000;
        endcase
    end

endmodule

alu.v
module alu (
    input  [31:0] a,
    input  [31:0] b,
    input  [3:0]  alu_ctrl,
    output reg [31:0] result,
    output        zero
);

    always @(*) begin
        case (alu_ctrl)
            4'b0000: result = a + b;
            4'b0001: result = a - b;
            4'b0010: result = a & b;
            4'b0011: result = a | b;
            4'b0100: result = a ^ b;
            4'b0101: result = ($signed(a) < $signed(b));
            4'b0110: result = a << b[4:0];
            4'b0111: result = a >> b[4:0];
            4'b1000: result = $signed(a) >>> b[4:0];
            default: result = 32'b0;
        endcase
    end

    assign zero = (result == 0);

endmodule

sign_extender.v
module sign_extender (
    input  [31:0] instr,
    output [31:0] imm_i,
    output [31:0] imm_s,
    output [31:0] imm_b,
    output [31:0] imm_u,
    output [31:0] imm_j
);

    assign imm_i = {{20{instr[31]}}, instr[31:20]};
    assign imm_s = {{20{instr[31]}}, instr[31:25], instr[11:7]};
    assign imm_b = {{19{instr[31]}}, instr[31], instr[7],
                    instr[30:25], instr[11:8], 1'b0};
    assign imm_u = {instr[31:12], 12'b0};
    assign imm_j = {{11{instr[31]}}, instr[31], instr[19:12],
                    instr[20], instr[30:21], 1'b0};

endmodule

regfile.v
module regfile (
    input        clk,
    input        we,
    input  [4:0] rs1,
    input  [4:0] rs2,
    input  [4:0] rd,
    input  [31:0] wd,
    output [31:0] rd1,
    output [31:0] rd2
);

    reg [31:0] rf [31:0];

    assign rd1 = (rs1 == 0) ? 32'b0 : rf[rs1];
    assign rd2 = (rs2 == 0) ? 32'b0 : rf[rs2];

    always @(posedge clk) begin
        if (we && rd != 0)
            rf[rd] <= wd;
    end

endmodule

mem.v
module mem (
    input        clk,
    input        we,
    input  [31:0] addr,
    input  [31:0] wd,
    output [31:0] rd
);

    // REQUIRED NAME
    reg [31:0] RAM [0:1023];

    assign rd = RAM[addr[11:2]];

    always @(posedge clk) begin
        if (we)
            RAM[addr[11:2]] <= wd;
    end

endmodule

rv_mc.v
`include "alu_decoder.v"
`include "alu.v"
`include "controller.v"
`include "mem.v"
`include "regfile.v"
`include "sign_extender.v"

module rv_mc (
    input clk,
    input rst
);

    // -------------------------------------------------
    // REGISTERS
    // -------------------------------------------------
    reg [31:0] pc;
    reg [31:0] instr;
    reg [31:0] alu_reg;
    reg [31:0] data_reg;
    reg [31:0] rd1_reg;
    reg [31:0] rd2_reg;

    // -------------------------------------------------
    // WIRES
    // -------------------------------------------------
    wire [31:0] mem_out;
    wire [31:0] alu_out;
    wire        zero;

    wire [31:0] imm_i, imm_s, imm_b, imm_u, imm_j;

    // CONTROL SIGNALS
    wire        sel_mem_addr;
    wire        ir_we;
    wire        pc_update;
    wire        mem_we;
    wire        rf_we;
    wire        sel_alu_src_a;
    wire [1:0]  sel_alu_src_b;
    wire [1:0]  alu_op;
    wire [1:0]  sel_result;

    // ALU control
    wire [3:0] alu_ctrl;

    // ALU inputs
    wire [31:0] alu_a;
    wire [31:0] alu_b;

    // WRITEBACK DATA
    wire [31:0] wb_data;

    // -------------------------------------------------
    // PC REGISTER
    // -------------------------------------------------
    always @(posedge clk or posedge rst) begin
        if (rst)
            pc <= 32'b0;
        else if (pc_update)
            pc <= alu_out;
    end

    // -------------------------------------------------
    // MEMORY (REQUIRED INSTANCE NAME)
    // -------------------------------------------------
    mem MEM (
        .clk(clk),
        .we(mem_we),
        .addr(sel_mem_addr ? alu_reg : pc),
        .wd(rd2_reg),
        .rd(mem_out)
    );

    // -------------------------------------------------
    // INSTRUCTION REGISTER
    // -------------------------------------------------
    always @(posedge clk) begin
        if (ir_we)
            instr <= mem_out;
    end

    // -------------------------------------------------
    // DATA REGISTER (for loads)
    // -------------------------------------------------
    always @(posedge clk) begin
        data_reg <= mem_out;
    end

    // -------------------------------------------------
    // REGISTER FILE
    // -------------------------------------------------
    wire [31:0] rd1, rd2;

    regfile RF (
        .clk(clk),
        .we(rf_we),
        .rs1(instr[19:15]),
        .rs2(instr[24:20]),
        .rd(instr[11:7]),
        .wd(wb_data),
        .rd1(rd1),
        .rd2(rd2)
    );

    // Latch register operands
    always @(posedge clk) begin
        rd1_reg <= rd1;
        rd2_reg <= rd2;
    end

    // -------------------------------------------------
    // SIGN EXTENDER
    // -------------------------------------------------
    sign_extender SE (
        .instr(instr),
        .imm_i(imm_i),
        .imm_s(imm_s),
        .imm_b(imm_b),
        .imm_u(imm_u),
        .imm_j(imm_j)
    );

    // -------------------------------------------------
    // ALU INPUT MUXES
    // -------------------------------------------------
    assign alu_a = sel_alu_src_a ? rd1_reg : pc;

    assign alu_b = (sel_alu_src_b == 2'b00) ? rd2_reg :
                   (sel_alu_src_b == 2'b01) ? imm_i :
                                               32'd4;

    // -------------------------------------------------
    // ALU
    // -------------------------------------------------
    alu ALU (
        .a(alu_a),
        .b(alu_b),
        .alu_ctrl(alu_ctrl),
        .result(alu_out),
        .zero(zero)
    );

    // Latch ALU result
    always @(posedge clk) begin
        alu_reg <= alu_out;
    end

    // -------------------------------------------------
    // ALU DECODER
    // -------------------------------------------------
    alu_decoder ALU_DEC (
        .alu_op(alu_op),
        .funct3(instr[14:12]),
        .funct7b5(instr[30]),
        .alu_ctrl(alu_ctrl)
    );

    // -------------------------------------------------
    // WRITEBACK MUX
    // -------------------------------------------------
    assign wb_data =
        (sel_result == 2'b00) ? alu_reg  :
        (sel_result == 2'b01) ? data_reg :
        (sel_result == 2'b10) ? pc + 4    :
                                imm_u;

    // -------------------------------------------------
    // CONTROLLER (FSM)
    // -------------------------------------------------
    controller CTRL (
        .clk(clk),
        .rst(rst),
        .opcode(instr[6:0]),
        .sel_mem_addr(sel_mem_addr),
        .ir_we(ir_we),
        .pc_update(pc_update),
        .mem_we(mem_we),
        .rf_we(rf_we),
        .sel_alu_src_a(sel_alu_src_a),
        .sel_alu_src_b(sel_alu_src_b),
        .alu_op(alu_op),
        .sel_result(sel_result)
    );

endmodule

tb.v
`include "rv_mc.v"
module tb;

    reg clk;
    reg rst;

    rv_mc DUT (
        .clk(clk),
        .rst(rst)
    );

    // Clock generation: 10 time units period
    always #5 clk = ~clk;

    initial begin
        // -----------------------------
        // LOAD PROGRAM INTO MEMORY
        // -----------------------------
        $readmemh("program.hex", DUT.MEM.RAM);

        $display("RAM[0] = %h", DUT.MEM.RAM[0]);
        $display("RAM[1] = %h", DUT.MEM.RAM[1]);
        $display("RAM[2] = %h", DUT.MEM.RAM[2]);


        $dumpfile("wave.vcd");
        $dumpvars(0, tb);


        // -----------------------------
        // RESET SEQUENCE
        // -----------------------------
        clk = 0;
        rst = 1;

        #20;
        rst = 0;

        // -----------------------------
        // RUN SIMULATION
        // -----------------------------
        #500;

        $display("Simulation finished");
        $finish;
    end

endmodule

wave.vcd
$date
	Fri Dec 19 23:09:14 2025
$end
$version
	Icarus Verilog
$end
$timescale
	1s
$end
$scope module tb $end
$var reg 1 ! clk $end
$var reg 1 " rst $end
$scope module DUT $end
$var wire 1 ! clk $end
$var wire 1 " rst $end
$var wire 1 # zero $end
$var wire 32 $ wb_data [31:0] $end
$var wire 2 % sel_result [1:0] $end
$var wire 1 & sel_mem_addr $end
$var wire 2 ' sel_alu_src_b [1:0] $end
$var wire 1 ( sel_alu_src_a $end
$var wire 1 ) rf_we $end
$var wire 32 * rd2 [31:0] $end
$var wire 32 + rd1 [31:0] $end
$var wire 1 , pc_update $end
$var wire 1 - mem_we $end
$var wire 32 . mem_out [31:0] $end
$var wire 1 / ir_we $end
$var wire 32 0 imm_u [31:0] $end
$var wire 32 1 imm_s [31:0] $end
$var wire 32 2 imm_j [31:0] $end
$var wire 32 3 imm_i [31:0] $end
$var wire 32 4 imm_b [31:0] $end
$var wire 32 5 alu_out [31:0] $end
$var wire 2 6 alu_op [1:0] $end
$var wire 4 7 alu_ctrl [3:0] $end
$var wire 32 8 alu_b [31:0] $end
$var wire 32 9 alu_a [31:0] $end
$var reg 32 : alu_reg [31:0] $end
$var reg 32 ; data_reg [31:0] $end
$var reg 32 < instr [31:0] $end
$var reg 32 = pc [31:0] $end
$var reg 32 > rd1_reg [31:0] $end
$var reg 32 ? rd2_reg [31:0] $end
$scope module ALU $end
$var wire 32 @ a [31:0] $end
$var wire 32 A b [31:0] $end
$var wire 1 # zero $end
$var wire 4 B alu_ctrl [3:0] $end
$var reg 32 C result [31:0] $end
$upscope $end
$scope module ALU_DEC $end
$var wire 3 D funct3 [2:0] $end
$var wire 1 E funct7b5 $end
$var wire 2 F alu_op [1:0] $end
$var reg 4 G alu_ctrl [3:0] $end
$upscope $end
$scope module CTRL $end
$var wire 1 ! clk $end
$var wire 7 H opcode [6:0] $end
$var wire 1 " rst $end
$var parameter 4 I S0_FETCH $end
$var parameter 4 J S10_JAL $end
$var parameter 4 K S11_LUI $end
$var parameter 4 L S1_DECODE $end
$var parameter 4 M S2_EXE_ADR $end
$var parameter 4 N S3_MEM_RD $end
$var parameter 4 O S4_WB_MEM $end
$var parameter 4 P S5_MEM_WR $end
$var parameter 4 Q S6_EXE_R $end
$var parameter 4 R S7_WB_ALU $end
$var parameter 4 S S8_BEQ $end
$var parameter 4 T S9_EXE_I $end
$var reg 2 U alu_op [1:0] $end
$var reg 1 / ir_we $end
$var reg 1 - mem_we $end
$var reg 4 V next_state [3:0] $end
$var reg 1 , pc_update $end
$var reg 1 ) rf_we $end
$var reg 1 ( sel_alu_src_a $end
$var reg 2 W sel_alu_src_b [1:0] $end
$var reg 1 & sel_mem_addr $end
$var reg 2 X sel_result [1:0] $end
$var reg 4 Y state [3:0] $end
$upscope $end
$scope module MEM $end
$var wire 32 Z addr [31:0] $end
$var wire 1 ! clk $end
$var wire 32 [ rd [31:0] $end
$var wire 32 \ wd [31:0] $end
$var wire 1 - we $end
$upscope $end
$scope module RF $end
$var wire 1 ! clk $end
$var wire 5 ] rd [4:0] $end
$var wire 5 ^ rs1 [4:0] $end
$var wire 5 _ rs2 [4:0] $end
$var wire 32 ` wd [31:0] $end
$var wire 1 ) we $end
$var wire 32 a rd2 [31:0] $end
$var wire 32 b rd1 [31:0] $end
$upscope $end
$scope module SE $end
$var wire 32 c instr [31:0] $end
$var wire 32 d imm_u [31:0] $end
$var wire 32 e imm_s [31:0] $end
$var wire 32 f imm_j [31:0] $end
$var wire 32 g imm_i [31:0] $end
$var wire 32 h imm_b [31:0] $end
$upscope $end
$upscope $end
$upscope $end
$enddefinitions $end
$comment Show the parameter values. $end
$dumpall
b1001 T
b1000 S
b111 R
b110 Q
b101 P
b100 O
b11 N
b10 M
b1 L
b1011 K
b1010 J
b0 I
$end
#0
$dumpvars
bx0 h
bx g
bx0 f
bx e
bx000000000000 d
bx c
bx b
bx a
bx `
bx _
bx ^
bx ]
bx \
b10000000010110111 [
b0 Z
b0 Y
b0 X
b10 W
b1 V
b0 U
bx H
b0 G
b0 F
xE
bx D
b100 C
b0 B
b100 A
b0 @
bx ?
bx >
b0 =
bx <
bx ;
bx :
b0 9
b100 8
b0 7
b0 6
b100 5
bx0 4
bx 3
bx0 2
bx 1
bx000000000000 0
1/
b10000000010110111 .
0-
1,
bx +
bx *
0)
0(
b10 '
0&
b0 %
bx $
0#
1"
0!
$end
#5
b0 *
b0 a
b1 V
b10 ^
b0 _
b1 ]
b0 D
0E
b110111 H
b0 3
b0 g
b1 1
b1 e
b100000000000 4
b100000000000 h
b10000000000000000 0
b10000000000000000 d
b10000000000000000 2
b10000000000000000 f
b100 $
b100 `
b10000000010110111 <
b10000000010110111 c
b10000000010110111 ;
b100 :
1!
#10
0!
#15
b0 ?
b0 \
1!
#20
0!
0"
#25
b10100001000000010010011 .
b10100001000000010010011 [
b0 8
b0 A
b100 Z
b100 9
b100 @
b0 '
b0 W
0,
0/
b1011 V
b100 =
b1 Y
1!
#30
0!
#35
b10000000000000000 $
b10000000000000000 `
b11 %
b11 X
1)
b0 V
b1011 Y
b10100001000000010010011 ;
1!
#40
0!
#45
b1000 5
b1000 C
b100 8
b100 A
b100 $
b100 `
1,
b10 '
b10 W
1/
b0 %
b0 X
0)
b1 V
b0 Y
1!
#50
0!
#55
b0 8
b0 A
b1010000000000000100010011 .
b1010000000000000100010011 [
b1000 5
b1000 C
b10000000000000000 +
b10000000000000000 b
bx *
bx a
b0 '
b0 W
0,
0/
b1001 V
b1000 Z
b1000 9
b1000 @
b1000 $
b1000 `
b1 ^
b101 _
b10011 H
b101 3
b101 g
b10100001000000000000000 0
b10100001000000000000000 d
b1000100000000100 2
b1000100000000100 f
b1 Y
b1000 =
b1000 :
b10100001000000010010011 <
b10100001000000010010011 c
1!
#60
0!
#65
b10000000000000000 9
b10000000000000000 @
0#
b10000000000000101 5
b10000000000000101 C
b10 6
b10 F
b10 U
b1 '
b1 W
1(
b111 V
b101 8
b101 A
b1001 Y
b1010000000000000100010011 ;
bx ?
bx \
b10000000000000000 >
1!
#70
0!
#75
x#
bx 5
bx C
bx 8
bx A
b1000 9
b1000 @
1)
b0 6
b0 F
b0 U
b0 '
b0 W
0(
b0 V
b10000000000000101 $
b10000000000000101 `
b111 Y
b10000000000000101 :
1!
#80
0!
#85
0#
b1100 5
b1100 C
b100 8
b100 A
1,
b10 '
b10 W
1/
0)
b1 V
b10000000000000101 +
b10000000000000101 b
bx $
bx `
b0 Y
bx :
1!
#90
0!
#95
x#
bx 8
bx A
b1000001010000000100011 .
b1000001010000000100011 [
bx 5
bx C
b0 +
b0 b
b0 '
b0 W
0,
0/
b1001 V
b1100 Z
b1100 9
b1100 @
b1100 $
b1100 `
b0 ^
b10100 _
b10 ]
b10100 3
b10100 g
b10 1
b10 e
b10 4
b10 h
b1010000000000000000000000 0
b1010000000000000000000000 d
b10100 2
b10100 f
b1 Y
b1100 =
b1100 :
b10000000000000101 >
b1010000000000000100010011 <
b1010000000000000100010011 c
1!
#100
0!
#105
0#
b10100 5
b10100 C
b10100 8
b10100 A
b0 9
b0 @
b10 6
b10 F
b10 U
b1 '
b1 W
1(
b111 V
bx $
bx `
b1001 Y
b1000001010000000100011 ;
b0 >
bx :
1!
#110
0!
#115
x#
bx 5
bx C
bx 8
bx A
b1100 9
b1100 @
1)
b0 6
b0 F
b0 U
b0 '
b0 W
0(
b0 V
b10100 $
b10100 `
b111 Y
b10100 :
1!
#120
0!
#125
0#
b10000 5
b10000 C
b100 8
b100 A
1,
b10 '
b10 W
1/
0)
b1 V
bx $
bx `
b0 Y
bx :
1!
#130
0!
#135
x#
bx 8
bx A
b1010000110000011 .
b1010000110000011 [
bx 5
bx C
b10000000000000101 +
b10000000000000101 b
b10100 *
b10100 a
b0 '
b0 W
0,
0/
b10 V
b10000 Z
b10000 9
b10000 @
b10000 $
b10000 `
b1 ^
b10 _
b0 ]
b10 D
b100011 H
b10 3
b10 g
b0 1
b0 e
b0 4
b0 h
b1000001010000000000000 0
b1000001010000000000000 d
b1010000000000010 2
b1010000000000010 f
b1 Y
b10000 =
b10000 :
b1000001010000000100011 <
b1000001010000000100011 c
1!
#140
0!
#145
b10000000000000101 9
b10000000000000101 @
0#
b10000000000000111 5
b10000000000000111 C
b1 '
b1 W
1(
b101 V
b10 8
b10 A
bx $
bx `
b10 Y
b1010000110000011 ;
b10100 ?
b10100 \
b10000000000000101 >
bx :
1!
#150
0!
#155
b10100001000000010010011 .
b10100001000000010010011 [
b100100 5
b100100 C
b10000000000000111 Z
b10100 8
b10100 A
b10000 9
b10000 @
1-
1&
b0 '
b0 W
0(
b0 V
b10000000000000111 $
b10000000000000111 `
b101 Y
b10000000000000111 :
1!
#160
0!
#165
b10100 5
b10100 C
b100 8
b100 A
1,
b10 '
b10 W
1/
0-
0&
b1 V
b10000 Z
b100100 $
b100100 `
b0 Y
b1010000110000011 .
b1010000110000011 [
b10100001000000010010011 ;
b100100 :
1!
#170
0!
#175
b10100 8
b10100 A
b1000011000001000110011 .
b1000011000001000110011 [
b101000 5
b101000 C
b0 *
b0 a
b0 '
b0 W
0,
0/
b10 V
b10100 Z
b10100 9
b10100 @
b10100 $
b10100 `
b0 _
b11 ]
b11 H
b0 3
b0 g
b11 1
b11 e
b100000000010 4
b100000000010 h
b1010000000000000 0
b1010000000000000 d
b1010000000000000 2
b1010000000000000 f
b1 Y
b10100 =
b10100 :
b1010000110000011 ;
b1010000110000011 <
b1010000110000011 c
1!
#180
0!
#185
b10000000000000101 9
b10000000000000101 @
b10000000000000101 5
b10000000000000101 C
b1 '
b1 W
1(
b11 V
b0 8
b0 A
b101000 $
b101000 `
b10 Y
b1000011000001000110011 ;
b0 ?
b0 \
b101000 :
1!
#190
0!
#195
b10100 .
b10100 [
b10100 5
b10100 C
b10000000000000101 Z
b10100 9
b10100 @
1&
b0 '
b0 W
0(
b100 V
b10000000000000101 $
b10000000000000101 `
b11 Y
b10000000000000101 :
1!
#200
0!
#205
b1000011000001000110011 .
b1000011000001000110011 [
b1 %
b1 X
1)
0&
b0 V
b10100 Z
b10100 $
b10100 `
b100 Y
b10100 ;
b10100 :
1!
#210
0!
#215
b11000 5
b11000 C
b100 8
b100 A
1,
b10 '
b10 W
1/
b0 %
b0 X
0)
b1 V
b0 Y
b1000011000001000110011 ;
1!
#220
0!
#225
b1000000001100100000001010110011 .
b1000000001100100000001010110011 [
b0 8
b0 A
b10100 +
b10100 b
b10100 *
b10100 a
b11000 Z
b11000 9
b11000 @
b0 '
b0 W
0,
0/
b110 V
b11 ^
b10 _
b100 ]
b0 D
b110011 H
b10 3
b10 g
b100 1
b100 e
b100 4
b100 h
b1000011000000000000000 0
b1000011000000000000000 d
b11000000000000010 2
b11000000000000010 f
b11000 $
b11000 `
b11000 =
b1 Y
b1000011000001000110011 <
b1000011000001000110011 c
b11000 :
1!
#230
0!
#235
b10100 9
b10100 @
b101000 5
b101000 C
b10 6
b10 F
b10 U
1(
b111 V
b10100 8
b10100 A
b110 Y
b10100 ?
b10100 \
b10100 >
b1000000001100100000001010110011 ;
1!
#240
0!
#245
b101100 5
b101100 C
b11000 9
b11000 @
1)
b0 6
b0 F
b0 U
0(
b0 V
b101000 $
b101000 `
b111 Y
b101000 :
1!
#250
0!
#255
b11100 5
b11100 C
b100 8
b100 A
1,
b10 '
b10 W
1/
0)
b1 V
b101100 $
b101100 `
b0 Y
b101100 :
1!
#260
0!
#265
b1100101000011001100011 .
b1100101000011001100011 [
b110000 5
b110000 C
b10100 8
b10100 A
b101000 +
b101000 b
b11100 Z
b11100 9
b11100 @
b0 '
b0 W
0,
0/
b110 V
b100 ^
b11 _
b101 ]
1E
b10000000011 3
b10000000011 g
b10000000101 1
b10000000101 e
b110000000100 4
b110000000100 h
b1000000001100100000000000000000 0
b1000000001100100000000000000000 d
b100000110000000010 2
b100000110000000010 f
b11100 $
b11100 `
b11100 =
b1 Y
b1000000001100100000001010110011 <
b1000000001100100000001010110011 c
b11100 :
1!
#270
0!
#275
b10100 5
b10100 C
b1 7
b1 B
b1 G
b101000 9
b101000 @
b10 6
b10 F
b10 U
1(
b111 V
b110000 $
b110000 `
b110 Y
b110000 :
b101000 >
b1100101000011001100011 ;
1!
#280
0!
#285
b110000 5
b110000 C
b0 7
b0 B
b0 G
b11100 9
b11100 @
1)
b0 6
b0 F
b0 U
0(
b0 V
b10100 $
b10100 `
b111 Y
b10100 :
1!
#290
0!
#295
b100000 5
b100000 C
b100 8
b100 A
1,
b10 '
b10 W
1/
0)
b1 V
b110000 $
b110000 `
b0 Y
b110000 :
1!
#300
0!
#305
b110001100000000001100010011 .
b110001100000000001100010011 [
b110100 5
b110100 C
b10100 8
b10100 A
b10100 +
b10100 b
b100000 Z
b100000 9
b100000 @
b0 '
b0 W
0,
0/
b1000 V
b101 ^
b1100 ]
0E
b1100011 H
b11 3
b11 g
b1100 1
b1100 e
b1100 4
b1100 h
b1100101000000000000000 0
b1100101000000000000000 d
b101000100000000010 2
b101000100000000010 f
b100000 $
b100000 `
b100000 =
b1 Y
b1100101000011001100011 <
b1100101000011001100011 c
b100000 :
1!
#310
0!
#315
1#
b0 5
b0 C
b1 7
b1 B
b1 G
b10100 9
b10100 @
1,
b1 6
b1 F
b1 U
1(
b0 V
b110100 $
b110100 `
b1000 Y
b110100 :
b10100 >
b110001100000000001100010011 ;
1!
#320
0!
#325
0#
b100 5
b100 C
b10000000010110111 .
b10000000010110111 [
b100 8
b100 A
b0 7
b0 B
b0 G
b0 9
b0 @
b0 Z
b10 '
b10 W
1/
b0 6
b0 F
b0 U
0(
1,
b1 V
b0 $
b0 `
b0 =
b0 Y
b0 :
1!
#330
0!
#335
b10100 8
b10100 A
b10100 .
b10100 [
b11000 5
b11000 C
b0 *
b0 a
b0 '
b0 W
0,
0/
b1011 V
b100 Z
b100 9
b100 @
b100 $
b100 `
b10 ^
b0 _
b1 ]
b110111 H
b0 3
b0 g
b1 1
b1 e
b100000000000 4
b100000000000 h
b10000000000000000 0
b10000000000000000 d
b10000000000000000 2
b10000000000000000 f
b1 Y
b100 =
b100 :
b10000000010110111 ;
b10000000010110111 <
b10000000010110111 c
1!
#340
0!
#345
b100 5
b100 C
b11 %
b11 X
1)
b0 V
b0 8
b0 A
b10000000000000000 $
b10000000000000000 `
b1011 Y
b10100 ;
b0 ?
b0 \
b11000 :
1!
#350
0!
#355
b1000 5
b1000 C
b100 8
b100 A
b100 $
b100 `
1,
b10 '
b10 W
1/
b0 %
b0 X
0)
b1 V
b0 Y
b100 :
1!
#360
0!
#365
b1010000000000000100010011 .
b1010000000000000100010011 [
b0 8
b0 A
b0 +
b0 b
b1000 Z
b1000 9
b1000 @
b0 '
b0 W
0,
0/
b0 V
b0 ^
b0 ]
b10100 H
b0 1
b0 e
b0 4
b0 h
b0 0
b0 d
b0 2
b0 f
b1000 $
b1000 `
b1000 =
b1 Y
b10100 <
b10100 c
b1000 :
1!
#370
0!
#375
b1100 5
b1100 C
b100 8
b100 A
1,
b10 '
b10 W
1/
b1 V
b0 Y
b0 >
b1010000000000000100010011 ;
1!
#380
0!
#385
b1000001010000000100011 .
b1000001010000000100011 [
b0 8
b0 A
bx *
bx a
b1100 Z
b1100 9
b1100 @
b0 '
b0 W
0,
0/
b1001 V
b10100 _
b10 ]
b10011 H
b10100 3
b10100 g
b10 1
b10 e
b10 4
b10 h
b1010000000000000000000000 0
b1010000000000000000000000 d
b10100 2
b10100 f
b1100 $
b1100 `
b1100 =
b1 Y
b1010000000000000100010011 <
b1010000000000000100010011 c
b1100 :
1!
#390
0!
#395
b0 9
b0 @
0#
b10100 5
b10100 C
b10 6
b10 F
b10 U
b1 '
b1 W
1(
b111 V
b10100 8
b10100 A
b1001 Y
bx ?
bx \
b1000001010000000100011 ;
1!
#400
0!
#405
x#
bx 5
bx C
bx 8
bx A
b1100 9
b1100 @
1)
b0 6
b0 F
b0 U
b0 '
b0 W
0(
b0 V
b10100 $
b10100 `
b111 Y
b10100 :
1!
#410
0!
#415
0#
b10000 5
b10000 C
b100 8
b100 A
1,
b10 '
b10 W
1/
0)
b1 V
bx $
bx `
b0 Y
bx :
1!
#420
0!
#425
b1010000110000011 .
b1010000110000011 [
x#
bx 5
bx C
bx 8
bx A
b10000000000000000 +
b10000000000000000 b
b10100 *
b10100 a
b10000 Z
b10000 9
b10000 @
b0 '
b0 W
0,
0/
b10 V
b1 ^
b10 _
b0 ]
b10 D
b100011 H
b10 3
b10 g
b0 1
b0 e
b0 4
b0 h
b1000001010000000000000 0
b1000001010000000000000 d
b1010000000000010 2
b1010000000000010 f
b10000 $
b10000 `
b10000 =
b1 Y
b1000001010000000100011 <
b1000001010000000100011 c
b10000 :
1!
#430
0!
#435
b10000000000000000 9
b10000000000000000 @
0#
b10000000000000010 5
b10000000000000010 C
b1 '
b1 W
1(
b101 V
bx $
bx `
b10 8
b10 A
b10 Y
bx :
b10100 ?
b10100 \
b10000000000000000 >
b1010000110000011 ;
1!
#440
0!
